flab/BootManager.py
flab/DeviceManager.py
flab/Flab.py
flab/TaskManager.py
flab/UiManager.py
flab/__init__.py
flab/Templates/DeviceTemplate.py
flab/Templates/DriverTemplate.py
flab/Templates/ProtocolTemplate.py
flab/Templates/__init__.py
flab-2.0.11.dist-info/LICENSE
flab-2.0.11.dist-info/METADATA
flab-2.0.11.dist-info/WHEEL
flab-2.0.11.dist-info/top_level.txt
flab-2.0.11.dist-info/RECORD
