Metadata-Version: 2.1
Name: flab
Version: 2.0.11
Summary: A fast, flexible and fun framework for creating automated laboratories
Home-page: https://github.com/njoseGIT/flab
Author: Nicholas A. Jose
Author-email: njose40707@gmail.com
License: GNU GPL3
Requires-Python: >=3.9
License-File: LICENSE
